magcal/__init__.py
magcal/cli.py
magcal/core.py
magcal-1.0.1.dist-info/licenses/LICENSE
magcal-1.0.1.dist-info/METADATA
magcal-1.0.1.dist-info/WHEEL
magcal-1.0.1.dist-info/entry_points.txt
magcal-1.0.1.dist-info/top_level.txt
magcal-1.0.1.dist-info/RECORD
