Metadata-Version: 2.4
Name: magcal
Version: 1.0.1
Summary: Magnetometer calibration python CLI tool for robotics, drones, satellites, and embedded systems
Author-email: Lundeen Cahilly <lundeen.cahilly@gmail.com>
License: MIT
Project-URL: Homepage, https://github.com/lundeen06/magcal
Project-URL: Issues, https://github.com/lundeen06/magcal/issues
Keywords: magnetometer,calibration,compass,hard-iron,soft-iron,satellite,drone,embedded,magnetic-field,sensor-fusion,aerospace,cubesat,navigation,ellipsoid-fitting,bias-correction
Classifier: Development Status :: 4 - Beta
Classifier: Intended Audience :: Developers
Classifier: Intended Audience :: Science/Research
Classifier: Intended Audience :: Manufacturing
Classifier: License :: OSI Approved :: MIT License
Classifier: Programming Language :: Python :: 3
Classifier: Programming Language :: Python :: 3.8
Classifier: Programming Language :: Python :: 3.9
Classifier: Programming Language :: Python :: 3.10
Classifier: Programming Language :: Python :: 3.11
Classifier: Topic :: Scientific/Engineering
Classifier: Topic :: Scientific/Engineering :: Astronomy
Classifier: Topic :: Scientific/Engineering :: Physics
Classifier: Topic :: System :: Hardware
Classifier: Topic :: Software Development :: Embedded Systems
Classifier: Operating System :: OS Independent
Classifier: Environment :: Console
Requires-Python: >=3.8
License-File: LICENSE
Requires-Dist: numpy
Requires-Dist: scipy
Requires-Dist: matplotlib
Requires-Dist: pyserial
Requires-Dist: rich
Requires-Dist: click
Requires-Dist: questionary
Dynamic: license-file
